llmclient/__init__.py
llmclient/constants.py
llmclient/cost_tracker.py
llmclient/embeddings.py
llmclient/exceptions.py
llmclient/llms.py
llmclient/py.typed
llmclient/rate_limiter.py
llmclient/types.py
llmclient/utils.py
llmclient/version.py
fh_llm_client-0.1.0.dist-info/LICENSE
fh_llm_client-0.1.0.dist-info/METADATA
fh_llm_client-0.1.0.dist-info/WHEEL
fh_llm_client-0.1.0.dist-info/top_level.txt
fh_llm_client-0.1.0.dist-info/RECORD
