Metadata-Version: 2.2
Name: fh-llm-client
Version: 0.1.0
Summary: A client to provide LLM responses for FutureHouse applications.
Author-email: FutureHouse technical staff <hello@futurehouse.org>
License:                                  Apache License
Project-URL: issues, https://github.com/Future-House/llm-client/issues
Project-URL: repository, https://github.com/Future-House/llm-client
Classifier: Operating System :: OS Independent
Classifier: Programming Language :: Python :: 3 :: Only
Classifier: Programming Language :: Python :: 3.11
Classifier: Programming Language :: Python :: 3.12
Classifier: Programming Language :: Python :: 3.13
Classifier: Programming Language :: Python
Requires-Python: >=3.11
License-File: LICENSE
Requires-Dist: coredis
Requires-Dist: fhaviary>=0.14.0
Requires-Dist: limits
Requires-Dist: litellm>=1.60.2
Requires-Dist: pydantic<2.10.2,>=2.10.1,~=2.0
Requires-Dist: tiktoken>=0.4.0
Requires-Dist: typing-extensions; python_version <= "3.11"
Provides-Extra: deepseek
Requires-Dist: litellm>1.59.3; extra == "deepseek"
Provides-Extra: dev
Requires-Dist: fh-llm-client[deepseek,local,progress,typing,vcr]; extra == "dev"
Requires-Dist: fhaviary[xml]; extra == "dev"
Requires-Dist: ipython>=8; extra == "dev"
Requires-Dist: mypy>=1.8; extra == "dev"
Requires-Dist: pre-commit>=3.4; extra == "dev"
Requires-Dist: pylint-pydantic; extra == "dev"
Requires-Dist: pytest-asyncio; extra == "dev"
Requires-Dist: pytest-recording; extra == "dev"
Requires-Dist: pytest-rerunfailures; extra == "dev"
Requires-Dist: pytest-subtests; extra == "dev"
Requires-Dist: pytest-sugar; extra == "dev"
Requires-Dist: pytest-timer[colorama]; extra == "dev"
Requires-Dist: pytest-xdist; extra == "dev"
Requires-Dist: pytest>=8; extra == "dev"
Requires-Dist: python-dotenv; extra == "dev"
Requires-Dist: refurb>=2; extra == "dev"
Requires-Dist: typeguard; extra == "dev"
Provides-Extra: local
Requires-Dist: numpy; extra == "local"
Requires-Dist: sentence-transformers; extra == "local"
Provides-Extra: progress
Requires-Dist: tqdm; extra == "progress"
Provides-Extra: typing
Requires-Dist: types-tqdm; extra == "typing"
Provides-Extra: vcr
Requires-Dist: vcrpy>=6; extra == "vcr"
